Metadata-Version: 2.1
Name: scfm
Version: 0.0.1
Summary: General API for all foundation models in single-cell genomics.
Home-page: https://github.com/poseidonchan/scFoundationModels
Author: Yanshuo Chen
Author-email: poseidonchan@icloud.com
License: GPL-3.0 License
Platform: any
Requires-Python: >=3.7.1,<3.8
License-File: LICENSE
